__init__.py
slida/__init__.py
slida/application.py
slida/debug.py
slida/slida.png
slida/utils.py
slida/config/__init__.py
slida/config/base.py
slida/config/combined.py
slida/config/fields.py
slida/files/__init__.py
slida/files/dir_scanner.py
slida/files/file_order.py
slida/files/image_file.py
slida/files/manager.py
slida/qt/__init__.py
slida/qt/application_view.py
slida/qt/image_screen.py
slida/qt/image_screen_widget.py
slida/qt/image_view.py
slida/qt/toast.py
slida/qt/utils.py
slida/transitions/__init__.py
slida/transitions/base.py
slida/transitions/blur_effect.py
slida/transitions/flip.py
slida/transitions/opacity_effect.py
slida/transitions/pair.py
slida/transitions/slide.py
slida/transitions/sub_image.py
slida/transitions/various.py
slida-0.7.4.dist-info/licenses/LICENSE
slida-0.7.4.dist-info/METADATA
slida-0.7.4.dist-info/WHEEL
slida-0.7.4.dist-info/entry_points.txt
slida-0.7.4.dist-info/top_level.txt
slida-0.7.4.dist-info/RECORD
