Metadata-Version: 2.4
Name: slida
Version: 0.7.4
Author-email: Robert Huselius <robert@huseli.us>
License-Expression: GPL-3.0-only
Project-URL: Homepage, https://github.com/Eboreg/slida
Project-URL: Issues, https://github.com/Eboreg/slida/issues
Project-URL: Source, https://github.com/Eboreg/slida
Classifier: Development Status :: 3 - Alpha
Classifier: Environment :: X11 Applications :: Qt
Classifier: Topic :: Multimedia :: Graphics :: Presentation
Classifier: Topic :: Multimedia :: Graphics :: Viewers
Requires-Python: >=3.10
License-File: LICENSE
Requires-Dist: klaatu-python
Requires-Dist: numpy
Requires-Dist: platformdirs
Requires-Dist: PySide6
Requires-Dist: pyyaml
Provides-Extra: dev
Requires-Dist: flake8; extra == "dev"
Requires-Dist: ipdb; extra == "dev"
Requires-Dist: ipython; extra == "dev"
Requires-Dist: isort; extra == "dev"
Requires-Dist: pylint; extra == "dev"
Dynamic: license-file
